promplate_trace-0.2.0.1.post1.dist-info/METADATA
promplate_trace-0.2.0.1.post1.dist-info/WHEEL
promplate_trace/__init__.py
promplate_trace/auto.py
promplate_trace/env.py
promplate_trace/langfuse.py
promplate_trace/langsmith.py
promplate_trace/utils.py
promplate_trace-0.2.0.1.post1.dist-info/RECORD
